README.rst
setup.py
bin/radiationDamageMPI
pysingfel/__init__.py
pysingfel/beam.py
pysingfel/crossTalk.py
pysingfel/detector.py
pysingfel/diffraction.py
pysingfel/geometry.py
pysingfel/particle.py
pysingfel/radiationDamage.py
pysingfel/radiationDamageMPI.py
pysingfel/util.py
pysingfel.egg-info/PKG-INFO
pysingfel.egg-info/SOURCES.txt
pysingfel.egg-info/dependency_links.txt
pysingfel.egg-info/not-zip-safe
pysingfel.egg-info/requires.txt
pysingfel.egg-info/top_level.txt
pysingfel/gpu/__init__.py
pysingfel/gpu/diffraction.py
pysingfel/gpu/geometry.py