Metadata-Version: 1.0
Name: pysingfel
Version: 0.2.1
Summary: Python version of singfel.
Home-page: https://github.com/Haoyuan-Li-93/pysingfel.git
Author: Haoyuan Li
Author-email: hyli16@stanford.edu
License: UNKNOWN
Platform: UNKNOWN
